{"includedIn":[],"title":"Imagine: John Lennon","slug":"imagine-john-lennon","synopsis":"Documentary lifting the lid on the former Beatle and solo artist. It was made possible by Lennon's wife, Yoko Ono - then smarting from the imminent release of Albert Goldman's kiss-and-savage biography - allowing the producers access to hundreds of hours of the couple's filmed diary, which Lennon kept for much of his post-Beatles life.","shortSynopsis":"The life and music of the former Beatle.","mediumSynopsis":"Documentary portrait of John Lennon, using interviews and archive film footage. Black-and-white and colour.","guidanceText":"flashing images, strong language","actors":[{"name":"John Lennon","slug":"john-lennon","rel":"person","id":"30b2908b-f610-40f6-a801-da518af8ba61","links":[{"rel":"search","href":"https://www.skystore.com/api/web/v2/catalog/assets/search/advanced/john-lennon?actor=John+Lennon","method":"GET","needsAuthentication":false},{"rel":"person","href":"https://www.skystore.com/api/web/v2/catalog/assets/actor/30b2908b-f610-40f6-a801-da518af8ba61/john-lennon","method":"GET","needsAuthentication":false}]},{"name":"Yoko Ono","slug":"yoko-ono","rel":"person","id":"619a8582-9ccf-4998-a6eb-deefc971016b","links":[{"rel":"search","href":"https://www.skystore.com/api/web/v2/catalog/assets/search/advanced/yoko-ono?actor=Yoko+Ono","method":"GET","needsAuthentication":false},{"rel":"person","href":"https://www.skystore.com/api/web/v2/catalog/assets/actor/619a8582-9ccf-4998-a6eb-deefc971016b/yoko-ono","method":"GET","needsAuthentication":false}]},{"name":"Paul McCartney","slug":"paul-mccartney","rel":"person","id":"630cedbb-14e7-4399-afed-b60028c7ebe0","links":[{"rel":"search","href":"https://www.skystore.com/api/web/v2/catalog/assets/search/advanced/paul-mccartney?actor=Paul+McCartney","method":"GET","needsAuthentication":false},{"rel":"person","href":"https://www.skystore.com/api/web/v2/catalog/assets/actor/630cedbb-14e7-4399-afed-b60028c7ebe0/paul-mccartney","method":"GET","needsAuthentication":false}]},{"name":"Ringo Starr","slug":"ringo-starr","rel":"person","id":"ca16b72b-db9b-4063-85c7-dff990134336","links":[{"rel":"search","href":"https://www.skystore.com/api/web/v2/catalog/assets/search/advanced/ringo-starr?actor=Ringo+Starr","method":"GET","needsAuthentication":false},{"rel":"person","href":"https://www.skystore.com/api/web/v2/catalog/assets/actor/ca16b72b-db9b-4063-85c7-dff990134336/ringo-starr","method":"GET","needsAuthentication":false}]},{"name":"George Harrison","slug":"george-harrison","rel":"person","id":"6e61d10a-adde-423c-9139-f8dbac65c496","links":[{"rel":"search","href":"https://www.skystore.com/api/web/v2/catalog/assets/search/advanced/george-harrison?actor=George+Harrison","method":"GET","needsAuthentication":false},{"rel":"person","href":"https://www.skystore.com/api/web/v2/catalog/assets/actor/6e61d10a-adde-423c-9139-f8dbac65c496/george-harrison","method":"GET","needsAuthentication":false}]}],"directors":[{"name":"Andrew Solt","slug":"andrew-solt","rel":"person","id":"c1d6b0be-b6e7-4d1a-bbdb-87b5ca6272a9","links":[{"rel":"search","href":"https://www.skystore.com/api/web/v2/catalog/assets/search/advanced/andrew-solt?director=Andrew+Solt","method":"GET","needsAuthentication":false},{"rel":"person","href":"https://www.skystore.com/api/web/v2/catalog/assets/director/c1d6b0be-b6e7-4d1a-bbdb-87b5ca6272a9/andrew-solt","method":"GET","needsAuthentication":false}]}],"ratings":[{"title":"15","rel":"rating","id":"590a0742-8467-4b8d-a6f9-c32e42b41a36","links":[{"rel":"image","href":"https://images.store.sky.com/api/img/direct/328B4E21-5B2B-4670-9B9E-CA039AE9D472_590A0742-8467-4B8D-A6F9-C32E42B41A36_200812218142.jpeg","needsAuthentication":false}]}],"duration":101,"year":1988,"dvdReleaseDate":"1988-10-28T00:00:00Z","countries":[],"genres":[{"key":"Factual","label":"Documentaries","rel":"genre","slug":"documentaries","id":"b7c4e7ae-7588-491d-a422-7151906bf71a","links":[{"rel":"genre","href":"https://www.skystore.com/api/web/v2/catalog/assets/genre/b7c4e7ae-7588-491d-a422-7151906bf71a/documentaries","method":"GET","needsAuthentication":false}]}],"offers":[{"assetId":"9c3e23e7-6d1b-4c04-a9c5-2f1838d31f37","price":"7.99","vat":0.2,"currency":"GBP","currencySymbol":"£","definition":"HD","description":"","type":"EST","videoOptions":{"options":{"deliveryProfile":{"allowDownload":true,"allowStreaming":true},"videos":[{"definition":"HD"},{"definition":"SD"}]},"videos":[{"videoCoding":"MSS_Streaming_HD_1280720_16-9","aspectRatio":"16:9","width":1280,"height":720,"bitrate":2.5,"audioLanguage":"en","audioFormat":"2 Channel Stereo","definition":"HD","deliveryFileName":"mss/i/ima/2342537/v6/eo-2342537-1-1_en_hd_169.ism","downloadSize":2758923492,"id":"3da458c7-b299-4dd0-b6f2-303c84db5c8d","drm":"PlayReady","embeddedSubtitles":false,"rel":"video","deliveryType":"mss_streaming","deliveryProfile":"","runtimeInSeconds":6098,"deliveryOptions":{"allowDownload":true,"allowStreaming":true}},{"videoCoding":"MSS_Streaming_SD_720576_16-9","aspectRatio":"16:9","width":720,"height":576,"bitrate":1.6,"audioLanguage":"en","audioFormat":"2 Channel Stereo","definition":"SD","deliveryFileName":"mss/i/ima/2342537/v6/eo-2342537-1-1_en_hd_169_sd.ism","downloadSize":1392385389,"id":"784803c9-7145-4c03-b753-a6fd3eed0a13","drm":"PlayReady","embeddedSubtitles":false,"rel":"video","deliveryType":"mss_streaming","deliveryProfile":"","runtimeInSeconds":6098,"deliveryOptions":{"allowDownload":true,"allowStreaming":true}}]},"options":{"deliveryProfile":{"allowDownload":true,"allowStreaming":true},"videos":[{"definition":"HD"},{"definition":"SD"}]},"title":"HD Digital + DVD","isPreferred":false,"physicalFulfilment":{"title":"DVD","isAvailableForDelivery":true},"availability":"Regular","isOnOffer":false,"expiryDate":"2018-04-15T23:59:59Z","id":"e9eb6f1f-1139-48e8-a481-081ccdd63cef","links":[{"rel":"paymentOptions","href":"https://www.skystore.com/api/web/v2/user/offers/e9eb6f1f-1139-48e8-a481-081ccdd63cef/imagine-john-lennon","method":"GET","needsAuthentication":true}]}],"rel":"asset","lastUpdateDate":"2017-03-17T06:00:02.15Z","assetType":"Programme","catalogSection":"Movies","isOnOffer":false,"id":"9c3e23e7-6d1b-4c04-a9c5-2f1838d31f37","links":[{"rel":"image","href":"https://images.store.sky.com/api/img/asset/en/66D8BB8A-E4E8-4422-9242-603110084545_D306D94B-4845-4D5B-B9EE-D946E604E909_2016-11-25-T17-11-52.jpg?s={{w}}x{{h}}","needsAuthentication":false},{"rel":"backgroundImage","href":"https://images.store.sky.com/api/img/assetbackground/en/D26F51A8-7BCA-4B9F-987D-5397C85662C5_D306D94B-4845-4D5B-B9EE-D946E604E909_2016-11-25-T17-11-52.jpg?s={{w}}x{{h}}","needsAuthentication":false},{"rel":"favorite","href":"https://www.skystore.com/api/web/v2/user/assets/9c3e23e7-6d1b-4c04-a9c5-2f1838d31f37/favorites/imagine-john-lennon","method":"GET","needsAuthentication":true},{"rel":"entitlement","href":"https://www.skystore.com/api/web/v2/user/assets/9c3e23e7-6d1b-4c04-a9c5-2f1838d31f37/entitlements/imagine-john-lennon","method":"GET","needsAuthentication":true},{"rel":"userOptions","href":"https://www.skystore.com/api/web/v2/user/assets/9c3e23e7-6d1b-4c04-a9c5-2f1838d31f37/options/imagine-john-lennon","method":"GET","needsAuthentication":true}]}