{"includedIn":[],"title":"The Deadly Game","slug":"the-deadly-game","synopsis":"London-set thriller starring Toby Stephens as Riley, a professional thief who's hired to pull off the perfect heist only to find himself caught between maverick cop Parker (Rufus Sewell) and ruthless crime overlord Corso (Gabriel Byrne). Feature debut of Kidulthood and Adulthood producer George Isaac.","shortSynopsis":"Crime thriller, starring Toby Stephens.","mediumSynopsis":"Corrupt copper Rufus Sewell plots to stage a bank robbery in order to catch elusive crime lord Gabriel Byrne.","guidanceText":"flashing images, strong language, violence","actors":[{"name":"Gabriel Byrne","slug":"gabriel-byrne","rel":"person","id":"7ced42fa-0c7b-4bc9-a0e7-e9c1cfe76e95","links":[{"rel":"search","href":"https://www.skystore.com/api/web/v2/catalog/assets/search/advanced/gabriel-byrne?actor=Gabriel+Byrne","method":"GET","needsAuthentication":false},{"rel":"person","href":"https://www.skystore.com/api/web/v2/catalog/assets/actor/7ced42fa-0c7b-4bc9-a0e7-e9c1cfe76e95/gabriel-byrne","method":"GET","needsAuthentication":false}]},{"name":"Rufus Sewell","slug":"rufus-sewell","rel":"person","id":"c1613f52-907f-4d43-b88a-e859db0a7d95","links":[{"rel":"search","href":"https://www.skystore.com/api/web/v2/catalog/assets/search/advanced/rufus-sewell?actor=Rufus+Sewell","method":"GET","needsAuthentication":false},{"rel":"person","href":"https://www.skystore.com/api/web/v2/catalog/assets/actor/c1613f52-907f-4d43-b88a-e859db0a7d95/rufus-sewell","method":"GET","needsAuthentication":false}]},{"name":"Toby Stephens","slug":"toby-stephens","rel":"person","id":"b1b790d3-78f1-490a-9ae4-1d5f8d380d3e","links":[{"rel":"search","href":"https://www.skystore.com/api/web/v2/catalog/assets/search/advanced/toby-stephens?actor=Toby+Stephens","method":"GET","needsAuthentication":false},{"rel":"person","href":"https://www.skystore.com/api/web/v2/catalog/assets/actor/b1b790d3-78f1-490a-9ae4-1d5f8d380d3e/toby-stephens","method":"GET","needsAuthentication":false}]},{"name":"Mark Badham","slug":"mark-badham","rel":"person","id":"142bb444-dcd9-438c-99b8-b09cc6201f20","links":[{"rel":"search","href":"https://www.skystore.com/api/web/v2/catalog/assets/search/advanced/mark-badham?actor=Mark+Badham","method":"GET","needsAuthentication":false},{"rel":"person","href":"https://www.skystore.com/api/web/v2/catalog/assets/actor/142bb444-dcd9-438c-99b8-b09cc6201f20/mark-badham","method":"GET","needsAuthentication":false}]}],"directors":[{"name":"George Isaac","slug":"george-isaac","rel":"person","id":"5beae57b-4b9c-461d-b922-836d11faa608","links":[{"rel":"search","href":"https://www.skystore.com/api/web/v2/catalog/assets/search/advanced/george-isaac?director=George+Isaac","method":"GET","needsAuthentication":false},{"rel":"person","href":"https://www.skystore.com/api/web/v2/catalog/assets/director/5beae57b-4b9c-461d-b922-836d11faa608/george-isaac","method":"GET","needsAuthentication":false}]}],"ratings":[{"title":"15","rel":"rating","id":"590a0742-8467-4b8d-a6f9-c32e42b41a36","links":[{"rel":"image","href":"https://images.store.sky.com/api/img/direct/328B4E21-5B2B-4670-9B9E-CA039AE9D472_590A0742-8467-4B8D-A6F9-C32E42B41A36_200812218142.jpeg","needsAuthentication":false}]}],"duration":81,"year":2013,"dvdReleaseDate":"2013-01-06T00:00:00Z","countries":[],"genres":[{"key":"Thriller","label":"Thriller","rel":"genre","slug":"thriller","id":"b6213e82-e533-4acf-bdf1-5acccbd41d34","links":[{"rel":"genre","href":"https://www.skystore.com/api/web/v2/catalog/assets/genre/b6213e82-e533-4acf-bdf1-5acccbd41d34/thriller","method":"GET","needsAuthentication":false}]}],"offers":[{"assetId":"b5486102-b9e3-4be6-93b1-179e5da235e4","price":"3.49","vat":0.2,"currency":"GBP","currencySymbol":"£","definition":"SD","description":"","type":"TVOD","videoOptions":{"options":{"deliveryProfile":{"allowDownload":false,"allowStreaming":true},"videos":[{"definition":"SD"}]},"videos":[{"videoCoding":"MSS_Streaming_SD_720576_16-9","aspectRatio":"16:9","width":720,"height":576,"bitrate":1.6,"audioLanguage":"en","audioFormat":"2 Channel Stereo","definition":"SD","deliveryFileName":"mss/d/dea/deadlygametheUNS_en_hd_169/deadlygametheUNS_en_hd_169_SD.ism","downloadSize":1027802581,"id":"d87822c9-b381-430f-9b09-720787fad130","drm":"PlayReady","embeddedSubtitles":false,"rel":"video","deliveryType":"mss_streaming","runtimeInSeconds":4860,"deliveryOptions":{"allowDownload":false,"allowStreaming":true}}]},"options":{"deliveryProfile":{"allowDownload":false,"allowStreaming":true},"videos":[{"definition":"SD"}]},"title":"HD Digital + DVD","isPreferred":false,"physicalFulfilment":{"title":"DVD","isAvailableForDelivery":true},"availability":"Regular","isOnOffer":false,"expiryDate":"2017-04-30T23:59:59Z","id":"f9808994-a33c-40a0-bb7f-edb972729b48","links":[{"rel":"paymentOptions","href":"https://www.skystore.com/api/web/v2/user/offers/f9808994-a33c-40a0-bb7f-edb972729b48/the-deadly-game","method":"GET","needsAuthentication":true}]},{"assetId":"b5486102-b9e3-4be6-93b1-179e5da235e4","price":"7.99","vat":0.2,"currency":"GBP","currencySymbol":"£","definition":"HD","description":"","type":"EST","videoOptions":{"options":{"deliveryProfile":{"allowDownload":true,"allowStreaming":true},"videos":[{"definition":"HD"},{"definition":"SD"}]},"videos":[{"videoCoding":"MSS_Streaming_HD_1280720_16-9","aspectRatio":"16:9","width":1280,"height":720,"bitrate":2.5,"audioLanguage":"en","audioFormat":"2 Channel Stereo","definition":"HD","deliveryFileName":"mss/d/dea/deadlygametheUNS_en_hd_169/deadlygametheUNS_en_hd_169.ism","downloadSize":2118623911,"id":"8355bfbd-51cb-4dc9-8645-7d14c9008964","drm":"PlayReady","embeddedSubtitles":false,"rel":"video","deliveryType":"mss_streaming","runtimeInSeconds":4860,"deliveryOptions":{"allowDownload":true,"allowStreaming":true}},{"videoCoding":"MSS_Streaming_SD_720576_16-9","aspectRatio":"16:9","width":720,"height":576,"bitrate":1.6,"audioLanguage":"en","audioFormat":"2 Channel Stereo","definition":"SD","deliveryFileName":"mss/d/dea/deadlygametheUNS_en_hd_169/deadlygametheUNS_en_hd_169_SD.ism","downloadSize":1027802581,"id":"d87822c9-b381-430f-9b09-720787fad130","drm":"PlayReady","embeddedSubtitles":false,"rel":"video","deliveryType":"mss_streaming","runtimeInSeconds":4860,"deliveryOptions":{"allowDownload":true,"allowStreaming":true}}]},"options":{"deliveryProfile":{"allowDownload":true,"allowStreaming":true},"videos":[{"definition":"HD"},{"definition":"SD"}]},"title":"HD Digital + DVD","isPreferred":false,"physicalFulfilment":{"title":"DVD","isAvailableForDelivery":true},"availability":"Regular","isOnOffer":false,"expiryDate":"2017-04-30T23:59:59Z","id":"5821188e-a188-4de8-911e-8242f1f1a424","links":[{"rel":"paymentOptions","href":"https://www.skystore.com/api/web/v2/user/offers/5821188e-a188-4de8-911e-8242f1f1a424/the-deadly-game","method":"GET","needsAuthentication":true}]}],"rel":"asset","lastUpdateDate":"2017-03-29T08:10:03.703Z","assetType":"Programme","catalogSection":"Movies","isOnOffer":false,"id":"b5486102-b9e3-4be6-93b1-179e5da235e4","links":[{"rel":"image","href":"https://images.store.sky.com/api/img/asset/en/66D8BB8A-E4E8-4422-9242-603110084545_D7357C28-5EC3-4B0B-91A0-1C071AD28C8D_2017-3-21-T20-51-13.jpg?s={{w}}x{{h}}","needsAuthentication":false},{"rel":"backgroundImage","href":"https://images.store.sky.com/api/img/assetbackground/en/D26F51A8-7BCA-4B9F-987D-5397C85662C5_D7357C28-5EC3-4B0B-91A0-1C071AD28C8D_2017-3-21-T20-51-13.jpg?s={{w}}x{{h}}","needsAuthentication":false},{"rel":"favorite","href":"https://www.skystore.com/api/web/v2/user/assets/b5486102-b9e3-4be6-93b1-179e5da235e4/favorites/the-deadly-game","method":"GET","needsAuthentication":true},{"rel":"entitlement","href":"https://www.skystore.com/api/web/v2/user/assets/b5486102-b9e3-4be6-93b1-179e5da235e4/entitlements/the-deadly-game","method":"GET","needsAuthentication":true},{"rel":"userOptions","href":"https://www.skystore.com/api/web/v2/user/assets/b5486102-b9e3-4be6-93b1-179e5da235e4/options/the-deadly-game","method":"GET","needsAuthentication":true}]}